pygments_onehalf/__init__.py
pygments_onehalf/onehalf.py
pygments_onehalf/py.typed
pygments_onehalf-1.0.0.dist-info/entry_points.txt
pygments_onehalf-1.0.0.dist-info/LICENSE.md
pygments_onehalf-1.0.0.dist-info/WHEEL
pygments_onehalf-1.0.0.dist-info/METADATA
pygments_onehalf-1.0.0.dist-info/RECORD
