Metadata-Version: 2.1
Name: pygments-onehalf
Version: 1.0.0
Summary: One Half color scheme for Pygments.
Home-page: https://gitlab.com/tomwatson1024/pygments-onehalf
Author: Tom W
Author-email: 796618-tomwatson1024@users.noreply.gitlab.com
Requires-Python: >=3.6,<4.0
Classifier: Programming Language :: Python :: 3
Classifier: Programming Language :: Python :: 3.6
Classifier: Programming Language :: Python :: 3.7
Classifier: Programming Language :: Python :: 3.8
Classifier: Programming Language :: Python :: 3.9
Requires-Dist: Pygments (>=2.10.0,<3.0.0)
Project-URL: Repository, https://gitlab.com/tomwatson1024/pygments-onehalf
